deepswarm/__init__.py
deepswarm/aco.py
deepswarm/backends.py
deepswarm/deepswarm.py
deepswarm/log.py
deepswarm/nodes.py
deepswarm/storage.py
settings/default.yaml
deepswarm-0.0.10.dist-info/LICENSE
deepswarm-0.0.10.dist-info/METADATA
deepswarm-0.0.10.dist-info/WHEEL
deepswarm-0.0.10.dist-info/top_level.txt
deepswarm-0.0.10.dist-info/RECORD
