Metadata-Version: 2.1
Name: deepswarm
Version: 0.0.10
Summary: Neural Architecture Search Powered by Swarm Intelligence
Home-page: https://github.com/Pattio/DeepSwarm
Author: Edvinas Byla
Author-email: edvinasbyla@gmail.com
License: UNKNOWN
Platform: UNKNOWN
Classifier: Programming Language :: Python :: 3.6
Classifier: License :: OSI Approved :: MIT License
Classifier: Operating System :: OS Independent
Requires-Dist: colorama (==0.4.1)
Requires-Dist: pyyaml (==5.1)
Requires-Dist: scikit-learn (==0.20.3)
